subtoml.py
subtoml-0.3.0.dist-info/DESCRIPTION.rst
subtoml-0.3.0.dist-info/METADATA
subtoml-0.3.0.dist-info/RECORD
subtoml-0.3.0.dist-info/WHEEL
subtoml-0.3.0.dist-info/entry_points.txt
subtoml-0.3.0.dist-info/metadata.json
subtoml-0.3.0.dist-info/top_level.txt
