Metadata-Version: 2.0
Name: subtoml
Version: 0.3.0
Summary: Sed for TOML: subtitute parts of a TOML file
Home-page: https://bitbucket.org/dahlia/subtoml
Author: Hong Minhee
Author-email: hong.minhee@gmail.com
License: GPLv3 or later
Platform: UNKNOWN
Classifier: Development Status :: 4 - Beta
Classifier: Environment :: Console
Classifier: Intended Audience :: Developers
Classifier: Intended Audience :: End Users/Desktop
Classifier: Intended Audience :: System Administrators
Classifier: License :: OSI Approved :: GNU General Public License v3 or later (GPLv3+)
Classifier: Operating System :: POSIX
Classifier: Programming Language :: Python :: 2.6
Classifier: Programming Language :: Python :: 2.7
Classifier: Programming Language :: Python :: 3.3
Classifier: Programming Language :: Python :: 3.4
Classifier: Programming Language :: Python :: 3.5
Classifier: Programming Language :: Python :: 3.6
Classifier: Programming Language :: Python :: Implementation :: CPython
Classifier: Programming Language :: Python :: Implementation :: PyPy
Classifier: Programming Language :: Python :: Implementation :: Stackless
Classifier: Topic :: Software Development :: Pre-processors
Classifier: Topic :: Text Editors :: Text Processing
Classifier: Topic :: Text Processing :: Filters
Classifier: Topic :: Utilities
Requires-Dist: pytoml (>=0.1.12)
